crudl/__init__.py
crudl/crudl_db.py
crudl/mysql_db.py
crudl/sqlite_db.py
crudl/test.py
evonik_crudl-0.0.2.dist-info/LICENSE
evonik_crudl-0.0.2.dist-info/METADATA
evonik_crudl-0.0.2.dist-info/WHEEL
evonik_crudl-0.0.2.dist-info/top_level.txt
evonik_crudl-0.0.2.dist-info/RECORD
