Metadata-Version: 2.1
Name: evonik-crudl
Version: 0.0.2
Summary: CRUDL wrappers for databases
Home-page: https://evodl.visualstudio.com
Author: Benjamin Schiller
Author-email: benjamin.schiller@evonik.com
License: UNKNOWN
Platform: UNKNOWN
Classifier: Programming Language :: Python :: 3
Classifier: License :: OSI Approved :: MIT License
Classifier: Operating System :: OS Independent
Requires-Python: >=3.6
Requires-Dist: mysql-connector
